tag/__init__.py
tag/__main__.py
tag_aaron_alphabet-1.0.1.dist-info/METADATA
tag_aaron_alphabet-1.0.1.dist-info/WHEEL
tag_aaron_alphabet-1.0.1.dist-info/entry_points.txt
tag_aaron_alphabet-1.0.1.dist-info/top_level.txt
tag_aaron_alphabet-1.0.1.dist-info/RECORD
