Metadata-Version: 2.1
Name: tag-aaron-alphabet
Version: 1.0.1
Summary: tagging files
Author-email: Aaron Alphabet <aaron.alphabet@gmx.ch>
Classifier: License :: OSI Approved :: MIT License
Classifier: Programming Language :: Python :: 3
Requires-Python: >=3.10
Requires-Dist: tomli-w
